cdscore/__init__.py
cdscore/abstracts.py
cdscore/action.py
cdscore/components.py
cdscore/constants.py
cdscore/event.py
cdscore/exceptions.py
cdscore/helpers.py
cdscore/intent.py
cdscore/rules.py
cdscore/types.py
cdscore/uielements.py
cdscore/web.py
cdscore-0.0.12.dist-info/licenses/LICENSE
cdscore-0.0.12.dist-info/METADATA
cdscore-0.0.12.dist-info/WHEEL
cdscore-0.0.12.dist-info/top_level.txt
cdscore-0.0.12.dist-info/RECORD
